dufuz/__init__.py
dufuz/__main__.py
dufuz/defuzzify.py
dufuz/dfn.py
dufuz/monitor.py
dufuz/negation.py
dufuz/tnorm.py
dufuz/core/__init__.py
dufuz/core/domain.py
dufuz/core/environment.py
dufuz/core/number.py
dufuz/interpreter/__init__.py
dufuz/interpreter/interpret.py
dufuz/interpreter/lexer.py
dufuz/interpreter/parser.py
dufuz-0.1.4.dist-info/METADATA
dufuz-0.1.4.dist-info/WHEEL
dufuz-0.1.4.dist-info/top_level.txt
dufuz-0.1.4.dist-info/RECORD
