Metadata-Version: 2.1
Name: dufuz
Version: 0.1.4
Summary: Discrete numeric fuzzy sets in Python algorithms.
Home-page: https://github.com/maniospas/dufuz
Author: Emmanouil (Manios) Krasanakis
Author-email: maniospas@hotmail.com
License: UNKNOWN
Platform: UNKNOWN
Classifier: Programming Language :: Python :: 3
Classifier: License :: OSI Approved :: Apache Software License
Classifier: Operating System :: OS Independent
Requires-Dist: numpy
Requires-Dist: torch
Requires-Dist: matplotlib
Requires-Dist: ply
